{
    "wall_time": 33.638301849365234, 
    "image_reports": [
        {
            "wall_time": 0.8043689727783203, 
            "image": "975.jpg", 
            "num_features": 1571
        }, 
        {
            "wall_time": 0.9500861167907715, 
            "image": "195.jpg", 
            "num_features": 1515
        }, 
        {
            "wall_time": 0.8514559268951416, 
            "image": "705.jpg", 
            "num_features": 1615
        }, 
        {
            "wall_time": 0.8784680366516113, 
            "image": "1215.jpg", 
            "num_features": 1505
        }, 
        {
            "wall_time": 0.9489741325378418, 
            "image": "1290.jpg", 
            "num_features": 1572
        }, 
        {
            "wall_time": 0.7265439033508301, 
            "image": "345.jpg", 
            "num_features": 1455
        }, 
        {
            "wall_time": 1.2546470165252686, 
            "image": "45.jpg", 
            "num_features": 1494
        }, 
        {
            "wall_time": 2.4718289375305176, 
            "image": "480.jpg", 
            "num_features": 1549
        }, 
        {
            "wall_time": 2.341212034225464, 
            "image": "1155.jpg", 
            "num_features": 1508
        }, 
        {
            "wall_time": 2.2530410289764404, 
            "image": "1575.jpg", 
            "num_features": 1413
        }, 
        {
            "wall_time": 2.1568050384521484, 
            "image": "1335.jpg", 
            "num_features": 1514
        }, 
        {
            "wall_time": 2.304809093475342, 
            "image": "1275.jpg", 
            "num_features": 1478
        }, 
        {
            "wall_time": 2.146134853363037, 
            "image": "120.jpg", 
            "num_features": 1478
        }, 
        {
            "wall_time": 2.241364002227783, 
            "image": "135.jpg", 
            "num_features": 1537
        }, 
        {
            "wall_time": 2.1924829483032227, 
            "image": "300.jpg", 
            "num_features": 1524
        }, 
        {
            "wall_time": 2.214646100997925, 
            "image": "1425.jpg", 
            "num_features": 1521
        }, 
        {
            "wall_time": 2.2696800231933594, 
            "image": "420.jpg", 
            "num_features": 1575
        }, 
        {
            "wall_time": 2.1903560161590576, 
            "image": "60.jpg", 
            "num_features": 1474
        }, 
        {
            "wall_time": 2.2555010318756104, 
            "image": "1350.jpg", 
            "num_features": 1464
        }, 
        {
            "wall_time": 2.4523539543151855, 
            "image": "840.jpg", 
            "num_features": 1637
        }, 
        {
            "wall_time": 2.5095038414001465, 
            "image": "855.jpg", 
            "num_features": 1621
        }, 
        {
            "wall_time": 2.29091215133667, 
            "image": "1230.jpg", 
            "num_features": 1547
        }, 
        {
            "wall_time": 2.2783360481262207, 
            "image": "1065.jpg", 
            "num_features": 1582
        }, 
        {
            "wall_time": 2.2485508918762207, 
            "image": "225.jpg", 
            "num_features": 1526
        }, 
        {
            "wall_time": 2.2527499198913574, 
            "image": "645.jpg", 
            "num_features": 1536
        }, 
        {
            "wall_time": 2.3247909545898438, 
            "image": "795.jpg", 
            "num_features": 1614
        }, 
        {
            "wall_time": 2.2932491302490234, 
            "image": "1560.jpg", 
            "num_features": 1502
        }, 
        {
            "wall_time": 2.436953067779541, 
            "image": "765.jpg", 
            "num_features": 1636
        }, 
        {
            "wall_time": 2.44101619720459, 
            "image": "885.jpg", 
            "num_features": 1618
        }, 
        {
            "wall_time": 2.377410888671875, 
            "image": "285.jpg", 
            "num_features": 1514
        }, 
        {
            "wall_time": 2.265174150466919, 
            "image": "690.jpg", 
            "num_features": 1567
        }, 
        {
            "wall_time": 2.3239259719848633, 
            "image": "540.jpg", 
            "num_features": 1652
        }, 
        {
            "wall_time": 2.284552812576294, 
            "image": "945.jpg", 
            "num_features": 1597
        }, 
        {
            "wall_time": 2.0896010398864746, 
            "image": "1635.jpg", 
            "num_features": 1410
        }, 
        {
            "wall_time": 2.3741250038146973, 
            "image": "315.jpg", 
            "num_features": 1521
        }, 
        {
            "wall_time": 2.280405044555664, 
            "image": "1320.jpg", 
            "num_features": 1486
        }, 
        {
            "wall_time": 2.4712140560150146, 
            "image": "825.jpg", 
            "num_features": 1625
        }, 
        {
            "wall_time": 2.3076488971710205, 
            "image": "1185.jpg", 
            "num_features": 1537
        }, 
        {
            "wall_time": 2.1446948051452637, 
            "image": "105.jpg", 
            "num_features": 1413
        }, 
        {
            "wall_time": 2.177577018737793, 
            "image": "1515.jpg", 
            "num_features": 1429
        }, 
        {
            "wall_time": 2.3023340702056885, 
            "image": "90.jpg", 
            "num_features": 1528
        }, 
        {
            "wall_time": 2.3198599815368652, 
            "image": "465.jpg", 
            "num_features": 1572
        }, 
        {
            "wall_time": 2.166729211807251, 
            "image": "1470.jpg", 
            "num_features": 1460
        }, 
        {
            "wall_time": 2.207512855529785, 
            "image": "1650.jpg", 
            "num_features": 1374
        }, 
        {
            "wall_time": 2.38749098777771, 
            "image": "1080.jpg", 
            "num_features": 1615
        }, 
        {
            "wall_time": 2.162688970565796, 
            "image": "1545.jpg", 
            "num_features": 1454
        }, 
        {
            "wall_time": 2.3590190410614014, 
            "image": "375.jpg", 
            "num_features": 1563
        }, 
        {
            "wall_time": 2.2290239334106445, 
            "image": "1305.jpg", 
            "num_features": 1512
        }, 
        {
            "wall_time": 2.3167309761047363, 
            "image": "1020.jpg", 
            "num_features": 1571
        }, 
        {
            "wall_time": 2.2255589962005615, 
            "image": "1140.jpg", 
            "num_features": 1512
        }, 
        {
            "wall_time": 2.1748149394989014, 
            "image": "1485.jpg", 
            "num_features": 1426
        }, 
        {
            "wall_time": 2.2110321521759033, 
            "image": "30.jpg", 
            "num_features": 1496
        }, 
        {
            "wall_time": 2.198131799697876, 
            "image": "1590.jpg", 
            "num_features": 1426
        }, 
        {
            "wall_time": 2.2575788497924805, 
            "image": "1200.jpg", 
            "num_features": 1528
        }, 
        {
            "wall_time": 2.24471116065979, 
            "image": "1410.jpg", 
            "num_features": 1497
        }, 
        {
            "wall_time": 2.3266961574554443, 
            "image": "240.jpg", 
            "num_features": 1520
        }, 
        {
            "wall_time": 2.1395490169525146, 
            "image": "1455.jpg", 
            "num_features": 1439
        }, 
        {
            "wall_time": 2.3536810874938965, 
            "image": "1110.jpg", 
            "num_features": 1552
        }, 
        {
            "wall_time": 2.3983941078186035, 
            "image": "1035.jpg", 
            "num_features": 1600
        }, 
        {
            "wall_time": 2.1375248432159424, 
            "image": "1440.jpg", 
            "num_features": 1448
        }, 
        {
            "wall_time": 2.352907180786133, 
            "image": "900.jpg", 
            "num_features": 1500
        }, 
        {
            "wall_time": 2.138469934463501, 
            "image": "1605.jpg", 
            "num_features": 1407
        }, 
        {
            "wall_time": 2.1372809410095215, 
            "image": "1380.jpg", 
            "num_features": 1461
        }, 
        {
            "wall_time": 2.3211019039154053, 
            "image": "1050.jpg", 
            "num_features": 1580
        }, 
        {
            "wall_time": 2.3272950649261475, 
            "image": "570.jpg", 
            "num_features": 1580
        }, 
        {
            "wall_time": 2.2239999771118164, 
            "image": "150.jpg", 
            "num_features": 1511
        }, 
        {
            "wall_time": 2.2095749378204346, 
            "image": "585.jpg", 
            "num_features": 1498
        }, 
        {
            "wall_time": 2.287454128265381, 
            "image": "180.jpg", 
            "num_features": 1522
        }, 
        {
            "wall_time": 2.272378921508789, 
            "image": "1170.jpg", 
            "num_features": 1560
        }, 
        {
            "wall_time": 2.4654319286346436, 
            "image": "495.jpg", 
            "num_features": 1619
        }, 
        {
            "wall_time": 2.3154242038726807, 
            "image": "510.jpg", 
            "num_features": 1577
        }, 
        {
            "wall_time": 2.218762159347534, 
            "image": "330.jpg", 
            "num_features": 1484
        }, 
        {
            "wall_time": 2.3566479682922363, 
            "image": "870.jpg", 
            "num_features": 1635
        }, 
        {
            "wall_time": 2.3969411849975586, 
            "image": "525.jpg", 
            "num_features": 1632
        }, 
        {
            "wall_time": 2.4731521606445312, 
            "image": "450.jpg", 
            "num_features": 1683
        }, 
        {
            "wall_time": 2.3405749797821045, 
            "image": "720.jpg", 
            "num_features": 1644
        }, 
        {
            "wall_time": 2.228389024734497, 
            "image": "255.jpg", 
            "num_features": 1504
        }, 
        {
            "wall_time": 2.294656991958618, 
            "image": "615.jpg", 
            "num_features": 1566
        }, 
        {
            "wall_time": 2.220641851425171, 
            "image": "1260.jpg", 
            "num_features": 1505
        }, 
        {
            "wall_time": 2.1777520179748535, 
            "image": "1620.jpg", 
            "num_features": 1384
        }, 
        {
            "wall_time": 2.2104830741882324, 
            "image": "555.jpg", 
            "num_features": 1554
        }, 
        {
            "wall_time": 2.2654550075531006, 
            "image": "1365.jpg", 
            "num_features": 1469
        }, 
        {
            "wall_time": 2.3151679039001465, 
            "image": "270.jpg", 
            "num_features": 1521
        }, 
        {
            "wall_time": 2.2083802223205566, 
            "image": "600.jpg", 
            "num_features": 1548
        }, 
        {
            "wall_time": 2.4223787784576416, 
            "image": "435.jpg", 
            "num_features": 1602
        }, 
        {
            "wall_time": 2.3262670040130615, 
            "image": "735.jpg", 
            "num_features": 1659
        }, 
        {
            "wall_time": 2.263098955154419, 
            "image": "0.jpg", 
            "num_features": 1497
        }, 
        {
            "wall_time": 2.334398031234741, 
            "image": "165.jpg", 
            "num_features": 1532
        }, 
        {
            "wall_time": 2.268796920776367, 
            "image": "390.jpg", 
            "num_features": 1577
        }, 
        {
            "wall_time": 2.4223880767822266, 
            "image": "960.jpg", 
            "num_features": 1629
        }, 
        {
            "wall_time": 2.321017026901245, 
            "image": "750.jpg", 
            "num_features": 1609
        }, 
        {
            "wall_time": 2.398790121078491, 
            "image": "405.jpg", 
            "num_features": 1590
        }, 
        {
            "wall_time": 2.4163968563079834, 
            "image": "990.jpg", 
            "num_features": 1630
        }, 
        {
            "wall_time": 2.2845771312713623, 
            "image": "360.jpg", 
            "num_features": 1507
        }, 
        {
            "wall_time": 2.22644305229187, 
            "image": "675.jpg", 
            "num_features": 1545
        }, 
        {
            "wall_time": 2.275444984436035, 
            "image": "930.jpg", 
            "num_features": 1596
        }, 
        {
            "wall_time": 2.1284759044647217, 
            "image": "75.jpg", 
            "num_features": 1467
        }, 
        {
            "wall_time": 2.231174945831299, 
            "image": "1095.jpg", 
            "num_features": 1525
        }, 
        {
            "wall_time": 2.3804969787597656, 
            "image": "630.jpg", 
            "num_features": 1543
        }, 
        {
            "wall_time": 2.2128078937530518, 
            "image": "1530.jpg", 
            "num_features": 1451
        }, 
        {
            "wall_time": 2.288753032684326, 
            "image": "915.jpg", 
            "num_features": 1587
        }, 
        {
            "wall_time": 2.3098199367523193, 
            "image": "660.jpg", 
            "num_features": 1590
        }, 
        {
            "wall_time": 2.3400049209594727, 
            "image": "15.jpg", 
            "num_features": 1490
        }, 
        {
            "wall_time": 2.298619031906128, 
            "image": "1125.jpg", 
            "num_features": 1544
        }, 
        {
            "wall_time": 2.2684099674224854, 
            "image": "1245.jpg", 
            "num_features": 1541
        }, 
        {
            "wall_time": 2.209606885910034, 
            "image": "810.jpg", 
            "num_features": 1629
        }, 
        {
            "wall_time": 2.1082839965820312, 
            "image": "210.jpg", 
            "num_features": 1528
        }, 
        {
            "wall_time": 2.1452651023864746, 
            "image": "1005.jpg", 
            "num_features": 1593
        }, 
        {
            "wall_time": 1.8639881610870361, 
            "image": "780.jpg", 
            "num_features": 1616
        }, 
        {
            "wall_time": 1.7980620861053467, 
            "image": "1500.jpg", 
            "num_features": 1470
        }, 
        {
            "wall_time": 1.8087470531463623, 
            "image": "1395.jpg", 
            "num_features": 1489
        }
    ]
}